google/cloud/devtools/cloudbuild/__init__.py
google/cloud/devtools/cloudbuild/gapic_version.py
google/cloud/devtools/cloudbuild/py.typed
google/cloud/devtools/cloudbuild_v1/__init__.py
google/cloud/devtools/cloudbuild_v1/gapic_metadata.json
google/cloud/devtools/cloudbuild_v1/gapic_version.py
google/cloud/devtools/cloudbuild_v1/py.typed
google/cloud/devtools/cloudbuild_v1/services/__init__.py
google/cloud/devtools/cloudbuild_v1/services/cloud_build/__init__.py
google/cloud/devtools/cloudbuild_v1/services/cloud_build/async_client.py
google/cloud/devtools/cloudbuild_v1/services/cloud_build/client.py
google/cloud/devtools/cloudbuild_v1/services/cloud_build/pagers.py
google/cloud/devtools/cloudbuild_v1/services/cloud_build/transports/__init__.py
google/cloud/devtools/cloudbuild_v1/services/cloud_build/transports/base.py
google/cloud/devtools/cloudbuild_v1/services/cloud_build/transports/grpc.py
google/cloud/devtools/cloudbuild_v1/services/cloud_build/transports/grpc_asyncio.py
google/cloud/devtools/cloudbuild_v1/services/cloud_build/transports/rest.py
google/cloud/devtools/cloudbuild_v1/services/cloud_build/transports/rest_base.py
google/cloud/devtools/cloudbuild_v1/types/__init__.py
google/cloud/devtools/cloudbuild_v1/types/cloudbuild.py
google/cloud/devtools/cloudbuild_v2/__init__.py
google/cloud/devtools/cloudbuild_v2/gapic_metadata.json
google/cloud/devtools/cloudbuild_v2/gapic_version.py
google/cloud/devtools/cloudbuild_v2/py.typed
google/cloud/devtools/cloudbuild_v2/services/__init__.py
google/cloud/devtools/cloudbuild_v2/services/repository_manager/__init__.py
google/cloud/devtools/cloudbuild_v2/services/repository_manager/async_client.py
google/cloud/devtools/cloudbuild_v2/services/repository_manager/client.py
google/cloud/devtools/cloudbuild_v2/services/repository_manager/pagers.py
google/cloud/devtools/cloudbuild_v2/services/repository_manager/transports/__init__.py
google/cloud/devtools/cloudbuild_v2/services/repository_manager/transports/base.py
google_cloud_build-3.31.1.dist-info/LICENSE
google_cloud_build-3.31.1.dist-info/METADATA
google_cloud_build-3.31.1.dist-info/WHEEL
google_cloud_build-3.31.1.dist-info/top_level.txt
google_cloud_build-3.31.1.dist-info/RECORD
